<?xml version="1.0" encoding="UTF-8"?>
<!DOCTYPE ode SYSTEM "content.dtd">
<ode xmlns="http://www.intef.es/xsd/ode" version="2.0">
<userPreferences>
  <userPreference>
    <key>theme</key>
    <value>neo</value>
  </userPreference>
</userPreferences>
<odeResources>
  <odeResource>
    <key>odeId</key>
    <value>20260420190126RIGJPY</value>
  </odeResource>
  <odeResource>
    <key>odeVersionId</key>
    <value>20260420190126IGHPUU</value>
  </odeResource>
  <odeResource>
    <key>exe_version</key>
    <value>3.0</value>
  </odeResource>
</odeResources>
<odeProperties>
  <odeProperty>
    <key>pp_title</key>
    <value>Pequeños exploradores saludables</value>
  </odeProperty>
  <odeProperty>
    <key>pp_subtitle</key>
    <value>Pequeños Exploradores Saludables.</value>
  </odeProperty>
  <odeProperty>
    <key>pp_author</key>
    <value>Iria Flores</value>
  </odeProperty>
  <odeProperty>
    <key>pp_description</key>
    <value>- Centro de Interés: El conocimiento del propio cuerpo y la adquisición de hábitos de alimentación saludable.
- Nivel: 3 años.
- Temporalización: 3 semanas (aproximadamente 9 sesiones de 30 minutos).
- Materias Implicadas: Áreas de Crecimiento en Armonía, Descubrimiento y Exploración del Entorno y Comunicación y Representación de la Realidad.
- Idioma: Castellano.
- Descripción General: El alumnado identificará las partes principales de su cuerpo y clasificará alimentos saludables y no saludables mediante juegos en la pizarra digital interactiva (PDI) y actividades sensoriales manipulativas.
- Justificación (Basada en la rutina de problemas técnicos): La elección de estos recursos digitales se debe a que se busca crear un entorno de aprendizaje activo y, al mismo tiempo, preparado ante posibles problemas técnicos. Por eso, se han escogido herramientas que cargan rápido y que pueden usarse sin conexión a internet, evitando así interrupciones. Además, las actividades tienen un diseño sencillo, ya que los niños de 3 años aún están desarrollando su habilidad para manejar objetos con precisión. Por este motivo, los elementos son grandes y fáciles de mover, de manera que puedan utilizarlos sin dificultad, incluso si la pantalla no está perfectamente calibrada.</value>
  </odeProperty>
  <odeProperty>
    <key>pp_lang</key>
    <value>es</value>
  </odeProperty>
  <odeProperty>
    <key>pp_license</key>
    <value>creative commons: attribution - share alike 4.0</value>
  </odeProperty>
  <odeProperty>
    <key>pp_licenseUrl</key>
    <value>https://creativecommons.org/licenses/by-sa/4.0/</value>
  </odeProperty>
  <odeProperty>
    <key>pp_theme</key>
    <value>neo</value>
  </odeProperty>
  <odeProperty>
    <key>pp_exelearning_version</key>
    <value>v4.0.0-rc1</value>
  </odeProperty>
  <odeProperty>
    <key>pp_modified</key>
    <value>1776704179391</value>
  </odeProperty>
  <odeProperty>
    <key>pp_addExeLink</key>
    <value>true</value>
  </odeProperty>
  <odeProperty>
    <key>pp_addPagination</key>
    <value>true</value>
  </odeProperty>
  <odeProperty>
    <key>pp_addSearchBox</key>
    <value>true</value>
  </odeProperty>
  <odeProperty>
    <key>pp_addAccessibilityToolbar</key>
    <value>true</value>
  </odeProperty>
  <odeProperty>
    <key>pp_addMathJax</key>
    <value>true</value>
  </odeProperty>
  <odeProperty>
    <key>exportSource</key>
    <value>true</value>
  </odeProperty>
  <odeProperty>
    <key>pp_globalFont</key>
    <value>nunito</value>
  </odeProperty>
</odeProperties>
<odeNavStructures>
<odeNavStructure>
  <odePageId>page-mo7fj2nm-dx6jtx6j9</odePageId>
  <odeParentPageId></odeParentPageId>
  <pageName>Presentación y descripción del proyecto.</pageName>
  <odeNavStructureOrder>0</odeNavStructureOrder>
  <odeNavStructureProperties>
    <odeNavStructureProperty>
      <key>titlePage</key>
      <value>Presentación y descripción del proyecto.</value>
    </odeNavStructureProperty>
    <odeNavStructureProperty>
      <key>visibility</key>
      <value>true</value>
    </odeNavStructureProperty>
    <odeNavStructureProperty>
      <key>highlight</key>
      <value>false</value>
    </odeNavStructureProperty>
    <odeNavStructureProperty>
      <key>hidePageTitle</key>
      <value>false</value>
    </odeNavStructureProperty>
    <odeNavStructureProperty>
      <key>editableInPage</key>
      <value>false</value>
    </odeNavStructureProperty>
    <odeNavStructureProperty>
      <key>titlePage</key>
      <value>Presentación y descripción del proyecto.</value>
    </odeNavStructureProperty>
    <odeNavStructureProperty>
      <key>titleNode</key>
      <value>Presentación y descripción del proyecto.</value>
    </odeNavStructureProperty>
  </odeNavStructureProperties>
  <odePagStructures>
    <odePagStructure>
      <odePageId>page-mo7fj2nm-dx6jtx6j9</odePageId>
      <odeBlockId>block-1776528982224-n0tudo8ir</odeBlockId>
      <blockName>Descripción</blockName>
      <iconName></iconName>
      <odePagStructureOrder>0</odePagStructureOrder>
      <odePagStructureProperties>
        <odePagStructureProperty>
          <key>visibility</key>
          <value>true</value>
        </odePagStructureProperty>
        <odePagStructureProperty>
          <key>teacherOnly</key>
          <value>false</value>
        </odePagStructureProperty>
        <odePagStructureProperty>
          <key>allowToggle</key>
          <value>true</value>
        </odePagStructureProperty>
        <odePagStructureProperty>
          <key>minimized</key>
          <value>false</value>
        </odePagStructureProperty>
        <odePagStructureProperty>
          <key>cssClass</key>
          <value></value>
        </odePagStructureProperty>
      </odePagStructureProperties>
      <odeComponents>
        <odeComponent>
          <odePageId>page-mo7fj2nm-dx6jtx6j9</odePageId>
          <odeBlockId>block-1776528982224-n0tudo8ir</odeBlockId>
          <odeIdeviceId>idevice-1776528982222-4yahvbeg1</odeIdeviceId>
          <odeIdeviceTypeName>text</odeIdeviceTypeName>
          <htmlView><![CDATA[<div class="exe-text-template">
    <ul>
<li><span dir="auto" style="vertical-align: inherit;"><span dir="auto" style="vertical-align: inherit;"><strong>Centro de Interés: </strong>El conocimiento del propio cuerpo y la adquisición de hábitos de alimentación saludable.</span></span></li>
<li><span dir="auto" style="vertical-align: inherit;"><span dir="auto" style="vertical-align: inherit;"><strong>Nivel:</strong> 3 años.</span></span></li>
<li><span dir="auto" style="vertical-align: inherit;"><span dir="auto" style="vertical-align: inherit;"><strong>Temporalización:</strong> 3 semanas (aproximadamente 9 sesiones de 30 minutos)</span></span></li>
<li><span dir="auto" style="vertical-align: inherit;"><span dir="auto" style="vertical-align: inherit;"><strong>Materias Implicadas: </strong>Áreas de Crecimiento en Armonía, Descubrimiento y Exploración del Entorno y Comunicación y Representación de la Realidad. </span></span><br /><span dir="auto" style="vertical-align: inherit;"><span dir="auto" style="vertical-align: inherit;"></span></span></li>
<li><span dir="auto" style="vertical-align: inherit;"><span dir="auto" style="vertical-align: inherit;"><strong>Idioma: </strong>Castellano. </span></span><br /><span dir="auto" style="vertical-align: inherit;"><span dir="auto" style="vertical-align: inherit;"></span></span></li>
<li><span dir="auto" style="vertical-align: inherit;"><span dir="auto" style="vertical-align: inherit;"><strong>Descripción General:</strong> El alumno identificará las partes principales de su cuerpo y clasificará alimentos saludables y no saludables mediante juegos en la pizarra digital interactiva (PDI) y actividades sensoriales manipulativas. </span></span><br /><span dir="auto" style="vertical-align: inherit;"><span dir="auto" style="vertical-align: inherit;">Justificación (Basada en la rutina de problemas técnicos): La elección de estos recursos digitales se debe a que se busca crear un entorno de aprendizaje activo y, al mismo tiempo, preparado ante posibles problemas técnicos. Por eso, se han escogido herramientas que cargan rápido y que pueden usarse sin conexión a internet, evitando así interrupciones. Además, las actividades tienen un diseño sencillo, ya que los niños de 3 años aún están desarrollando su habilidad para manejar objetos con precisión. Por este motivo, los elementos son grandes y fáciles de mover, de manera que puedan utilizarlos sin dificultad, incluso si la pantalla no está perfectamente calibrada.</span></span></li>
</ul>
</div>]]></htmlView>
          <jsonProperties><![CDATA[{"ideviceId":"idevice-1776528982222-4yahvbeg1","textInfoDurationInput":"","textInfoDurationTextInput":"Duración","textInfoParticipantsInput":"","textInfoParticipantsTextInput":"Agrupamiento","textTextarea":"<ul>\n<li><span dir=\"auto\" style=\"vertical-align: inherit;\"><span dir=\"auto\" style=\"vertical-align: inherit;\"><strong>Centro de Interés: </strong>El conocimiento del propio cuerpo y la adquisición de hábitos de alimentación saludable.</span></span></li>\n<li><span dir=\"auto\" style=\"vertical-align: inherit;\"><span dir=\"auto\" style=\"vertical-align: inherit;\"><strong>Nivel:</strong> 3 años.</span></span></li>\n<li><span dir=\"auto\" style=\"vertical-align: inherit;\"><span dir=\"auto\" style=\"vertical-align: inherit;\"><strong>Temporalización:</strong> 3 semanas (aproximadamente 9 sesiones de 30 minutos)</span></span></li>\n<li><span dir=\"auto\" style=\"vertical-align: inherit;\"><span dir=\"auto\" style=\"vertical-align: inherit;\"><strong>Materias Implicadas: </strong>Áreas de Crecimiento en Armonía, Descubrimiento y Exploración del Entorno y Comunicación y Representación de la Realidad. </span></span><br /><span dir=\"auto\" style=\"vertical-align: inherit;\"><span dir=\"auto\" style=\"vertical-align: inherit;\"></span></span></li>\n<li><span dir=\"auto\" style=\"vertical-align: inherit;\"><span dir=\"auto\" style=\"vertical-align: inherit;\"><strong>Idioma: </strong>Castellano. </span></span><br /><span dir=\"auto\" style=\"vertical-align: inherit;\"><span dir=\"auto\" style=\"vertical-align: inherit;\"></span></span></li>\n<li><span dir=\"auto\" style=\"vertical-align: inherit;\"><span dir=\"auto\" style=\"vertical-align: inherit;\"><strong>Descripción General:</strong> El alumno identificará las partes principales de su cuerpo y clasificará alimentos saludables y no saludables mediante juegos en la pizarra digital interactiva (PDI) y actividades sensoriales manipulativas. </span></span><br /><span dir=\"auto\" style=\"vertical-align: inherit;\"><span dir=\"auto\" style=\"vertical-align: inherit;\">Justificación (Basada en la rutina de problemas técnicos): La elección de estos recursos digitales se debe a que se busca crear un entorno de aprendizaje activo y, al mismo tiempo, preparado ante posibles problemas técnicos. Por eso, se han escogido herramientas que cargan rápido y que pueden usarse sin conexión a internet, evitando así interrupciones. Además, las actividades tienen un diseño sencillo, ya que los niños de 3 años aún están desarrollando su habilidad para manejar objetos con precisión. Por este motivo, los elementos son grandes y fáciles de mover, de manera que puedan utilizarlos sin dificultad, incluso si la pantalla no está perfectamente calibrada.</span></span></li>\n</ul>","textFeedbackInput":"Mostrar retroalimentación","textFeedbackTextarea":""}]]></jsonProperties>
          <odeComponentsOrder>0</odeComponentsOrder>
          <odeComponentsProperties>
            <odeComponentsProperty>
              <key>visibility</key>
              <value>true</value>
            </odeComponentsProperty>
            <odeComponentsProperty>
              <key>teacherOnly</key>
              <value>false</value>
            </odeComponentsProperty>
            <odeComponentsProperty>
              <key>cssClass</key>
              <value></value>
            </odeComponentsProperty>
          </odeComponentsProperties>
        </odeComponent>
      </odeComponents>
    </odePagStructure>
  </odePagStructures>
</odeNavStructure>
<odeNavStructure>
  <odePageId>page-mo7fj2no-h5cmz53v0</odePageId>
  <odeParentPageId></odeParentPageId>
  <pageName>Protección de datos personales y garantías de derechos digitales </pageName>
  <odeNavStructureOrder>1</odeNavStructureOrder>
  <odeNavStructureProperties>
    <odeNavStructureProperty>
      <key>titlePage</key>
      <value>Protección de datos personales y garantías de derechos digitales </value>
    </odeNavStructureProperty>
    <odeNavStructureProperty>
      <key>visibility</key>
      <value>true</value>
    </odeNavStructureProperty>
    <odeNavStructureProperty>
      <key>highlight</key>
      <value>false</value>
    </odeNavStructureProperty>
    <odeNavStructureProperty>
      <key>hidePageTitle</key>
      <value>false</value>
    </odeNavStructureProperty>
    <odeNavStructureProperty>
      <key>editableInPage</key>
      <value>false</value>
    </odeNavStructureProperty>
    <odeNavStructureProperty>
      <key>titlePage</key>
      <value>Protección de datos personales y garantías de derechos digitales </value>
    </odeNavStructureProperty>
    <odeNavStructureProperty>
      <key>titleNode</key>
      <value></value>
    </odeNavStructureProperty>
  </odeNavStructureProperties>
  <odePagStructures>
    <odePagStructure>
      <odePageId>page-mo7fj2no-h5cmz53v0</odePageId>
      <odeBlockId>block-1776528825702-d800wonnr</odeBlockId>
      <blockName>Galería de imágenes</blockName>
      <iconName></iconName>
      <odePagStructureOrder>1</odePagStructureOrder>
      <odePagStructureProperties>
        <odePagStructureProperty>
          <key>visibility</key>
          <value>true</value>
        </odePagStructureProperty>
        <odePagStructureProperty>
          <key>teacherOnly</key>
          <value>false</value>
        </odePagStructureProperty>
        <odePagStructureProperty>
          <key>allowToggle</key>
          <value>true</value>
        </odePagStructureProperty>
        <odePagStructureProperty>
          <key>minimized</key>
          <value>false</value>
        </odePagStructureProperty>
        <odePagStructureProperty>
          <key>cssClass</key>
          <value></value>
        </odePagStructureProperty>
      </odePagStructureProperties>
      <odeComponents>
        <odeComponent>
          <odePageId>page-mo7fj2no-h5cmz53v0</odePageId>
          <odeBlockId>block-1776528825702-d800wonnr</odeBlockId>
          <odeIdeviceId>idevice-1776528825701-si4v70pjm</odeIdeviceId>
          <odeIdeviceTypeName>image-gallery</odeIdeviceTypeName>
          <htmlView><![CDATA[<!-- Idevice Example template start -->
<div class="exe-image-gallery-template">
  <!-- Idevice content start -->
  
            <div class="imageGallery-IDevice">
                <div class="imageGallery-body"><div id="imageContainer_0" class="imageContainer"> <a idevice-id="idevice-1776528825701-si4v70pjm" title="" href="{{context_path}}/content/resources/TIPS DIGITALES PARA FAMILIAS.png" class="imageLink">  <div class="imageElement">   <img src="{{context_path}}/content/resources/TIPS DIGITALES PARA FAMILIAS.png" height="128" width="128" title="" alt="" titlelink="" author="" authorlink="" license="" licenselink=""/>  </div> </a></div>
                </div>
            </div>
  <!-- Idevice content end -->
</div>
<!-- Idevice Example template end -->]]></htmlView>
          <jsonProperties><![CDATA[{"ideviceId":"idevice-1776528825701-si4v70pjm","img_0":{"img":"{{context_path}}/content/resources/TIPS DIGITALES PARA FAMILIAS.png","thumbnail":"{{context_path}}/content/resources/TIPS DIGITALES PARA FAMILIAS.png","title":"","linktitle":"","author":"","linkauthor":"","license":""}}]]></jsonProperties>
          <odeComponentsOrder>0</odeComponentsOrder>
          <odeComponentsProperties>
            <odeComponentsProperty>
              <key>visibility</key>
              <value>true</value>
            </odeComponentsProperty>
            <odeComponentsProperty>
              <key>teacherOnly</key>
              <value>false</value>
            </odeComponentsProperty>
            <odeComponentsProperty>
              <key>cssClass</key>
              <value></value>
            </odeComponentsProperty>
          </odeComponentsProperties>
        </odeComponent>
      </odeComponents>
    </odePagStructure>
  </odePagStructures>
</odeNavStructure>
<odeNavStructure>
  <odePageId>page-mo7fj2np-vky6v36jo</odePageId>
  <odeParentPageId></odeParentPageId>
  <pageName>Descripción del producto final </pageName>
  <odeNavStructureOrder>2</odeNavStructureOrder>
  <odeNavStructureProperties>
    <odeNavStructureProperty>
      <key>titlePage</key>
      <value>Descripción del producto final </value>
    </odeNavStructureProperty>
    <odeNavStructureProperty>
      <key>visibility</key>
      <value>true</value>
    </odeNavStructureProperty>
    <odeNavStructureProperty>
      <key>highlight</key>
      <value>false</value>
    </odeNavStructureProperty>
    <odeNavStructureProperty>
      <key>hidePageTitle</key>
      <value>false</value>
    </odeNavStructureProperty>
    <odeNavStructureProperty>
      <key>editableInPage</key>
      <value>false</value>
    </odeNavStructureProperty>
    <odeNavStructureProperty>
      <key>titlePage</key>
      <value>Descripción del producto final </value>
    </odeNavStructureProperty>
    <odeNavStructureProperty>
      <key>titleNode</key>
      <value></value>
    </odeNavStructureProperty>
  </odeNavStructureProperties>
  <odePagStructures>
    <odePagStructure>
      <odePageId>page-mo7fj2np-vky6v36jo</odePageId>
      <odeBlockId>block-1776529276695-01jqtt4x8</odeBlockId>
      <blockName>Texto</blockName>
      <iconName></iconName>
      <odePagStructureOrder>1</odePagStructureOrder>
      <odePagStructureProperties>
        <odePagStructureProperty>
          <key>visibility</key>
          <value>true</value>
        </odePagStructureProperty>
        <odePagStructureProperty>
          <key>teacherOnly</key>
          <value>false</value>
        </odePagStructureProperty>
        <odePagStructureProperty>
          <key>allowToggle</key>
          <value>true</value>
        </odePagStructureProperty>
        <odePagStructureProperty>
          <key>minimized</key>
          <value>false</value>
        </odePagStructureProperty>
        <odePagStructureProperty>
          <key>cssClass</key>
          <value></value>
        </odePagStructureProperty>
      </odePagStructureProperties>
      <odeComponents>
        <odeComponent>
          <odePageId>page-mo7fj2np-vky6v36jo</odePageId>
          <odeBlockId>block-1776529276695-01jqtt4x8</odeBlockId>
          <odeIdeviceId>idevice-1776529276694-5o6ggose5</odeIdeviceId>
          <odeIdeviceTypeName>text</odeIdeviceTypeName>
          <htmlView><![CDATA[<div class="exe-text-template">
    <p>La herramienta digital propuesta es Genially. El alumnado de Educación Infantil la utilizará para elaborar un producto final interactivo sobre cómo mantener un cuerpo y una vida saludable. El objetivo es que el alumnado organice y presente información relevante mediante textos, imágenes e hipervínculos a vídeos, fomentando así el aprendizaje significativo. Dada la edad del alumnado se trabajará en gran grupo en la pizarra digital con la ayuda de la maestra.</p>
<p>La elección de esta herramienta se justifica por su gran versatilidad, ya que permite crear contenidos visuales, dinámicos y atractivos de forma sencilla. Además, se adapta al contexto del centro y a la competencia digital del alumnado, facilitando su uso incluso en edades tempranas con apoyo docente. Con el apoyo adecuado, el alumnado aprenderá a escribir en el teclado, buscaremos las imágenes más idóneas para cada diapositiva, así como vincularemos vídeos buscados en YouTube relacionados con la temática que estamos trabajando y que hemos visto previamente en clase. Por último, el producto final podrá compartirse fácilmente con las familias, favoreciendo la implicación de estas y promoviendo hábitos de vida saludable también en el entorno familiar.</p>
</div>]]></htmlView>
          <jsonProperties><![CDATA[{"ideviceId":"idevice-1776529276694-5o6ggose5","textInfoDurationInput":"","textInfoDurationTextInput":"Duración","textInfoParticipantsInput":"","textInfoParticipantsTextInput":"Agrupamiento","textTextarea":"<p>La herramienta digital propuesta es Genially. El alumnado de Educación Infantil la utilizará para elaborar un producto final interactivo sobre cómo mantener un cuerpo y una vida saludable. El objetivo es que el alumnado organice y presente información relevante mediante textos, imágenes e hipervínculos a vídeos, fomentando así el aprendizaje significativo. Dada la edad del alumnado se trabajará en gran grupo en la pizarra digital con la ayuda de la maestra.</p>\n<p>La elección de esta herramienta se justifica por su gran versatilidad, ya que permite crear contenidos visuales, dinámicos y atractivos de forma sencilla. Además, se adapta al contexto del centro y a la competencia digital del alumnado, facilitando su uso incluso en edades tempranas con apoyo docente. Con el apoyo adecuado, el alumnado aprenderá a escribir en el teclado, buscaremos las imágenes más idóneas para cada diapositiva, así como vincularemos vídeos buscados en YouTube relacionados con la temática que estamos trabajando y que hemos visto previamente en clase. Por último, el producto final podrá compartirse fácilmente con las familias, favoreciendo la implicación de estas y promoviendo hábitos de vida saludable también en el entorno familiar.</p>","textFeedbackInput":"Mostrar retroalimentación","textFeedbackTextarea":""}]]></jsonProperties>
          <odeComponentsOrder>0</odeComponentsOrder>
          <odeComponentsProperties>
            <odeComponentsProperty>
              <key>visibility</key>
              <value>true</value>
            </odeComponentsProperty>
            <odeComponentsProperty>
              <key>teacherOnly</key>
              <value>false</value>
            </odeComponentsProperty>
            <odeComponentsProperty>
              <key>cssClass</key>
              <value></value>
            </odeComponentsProperty>
          </odeComponentsProperties>
        </odeComponent>
      </odeComponents>
    </odePagStructure>
  </odePagStructures>
</odeNavStructure>
<odeNavStructure>
  <odePageId>page-mo7fj2np-ozf28tvpv</odePageId>
  <odeParentPageId></odeParentPageId>
  <pageName>Herramientas de curación de contenidos</pageName>
  <odeNavStructureOrder>3</odeNavStructureOrder>
  <odeNavStructureProperties>
    <odeNavStructureProperty>
      <key>titlePage</key>
      <value>Herramientas de curación de contenidos</value>
    </odeNavStructureProperty>
    <odeNavStructureProperty>
      <key>visibility</key>
      <value>true</value>
    </odeNavStructureProperty>
    <odeNavStructureProperty>
      <key>highlight</key>
      <value>false</value>
    </odeNavStructureProperty>
    <odeNavStructureProperty>
      <key>hidePageTitle</key>
      <value>false</value>
    </odeNavStructureProperty>
    <odeNavStructureProperty>
      <key>editableInPage</key>
      <value>false</value>
    </odeNavStructureProperty>
    <odeNavStructureProperty>
      <key>titlePage</key>
      <value>Herramientas de curación de contenidos</value>
    </odeNavStructureProperty>
    <odeNavStructureProperty>
      <key>titleNode</key>
      <value>Herramientas de curación de contenidos</value>
    </odeNavStructureProperty>
  </odeNavStructureProperties>
  <odePagStructures>
  </odePagStructures>
</odeNavStructure>
<odeNavStructure>
  <odePageId>page-mo7fj2nq-af9ogzgnu</odePageId>
  <odeParentPageId>page-mo7fj2np-ozf28tvpv</odeParentPageId>
  <pageName>Symbaloo</pageName>
  <odeNavStructureOrder>0</odeNavStructureOrder>
  <odeNavStructureProperties>
    <odeNavStructureProperty>
      <key>titlePage</key>
      <value>Symbaloo</value>
    </odeNavStructureProperty>
    <odeNavStructureProperty>
      <key>visibility</key>
      <value>true</value>
    </odeNavStructureProperty>
    <odeNavStructureProperty>
      <key>highlight</key>
      <value>false</value>
    </odeNavStructureProperty>
    <odeNavStructureProperty>
      <key>hidePageTitle</key>
      <value>false</value>
    </odeNavStructureProperty>
    <odeNavStructureProperty>
      <key>editableInPage</key>
      <value>false</value>
    </odeNavStructureProperty>
    <odeNavStructureProperty>
      <key>titlePage</key>
      <value>Symbaloo</value>
    </odeNavStructureProperty>
    <odeNavStructureProperty>
      <key>titleNode</key>
      <value></value>
    </odeNavStructureProperty>
  </odeNavStructureProperties>
  <odePagStructures>
    <odePagStructure>
      <odePageId>page-mo7fj2nq-af9ogzgnu</odePageId>
      <odeBlockId>block-1776529688982-gzbfasqjv</odeBlockId>
      <blockName>Web</blockName>
      <iconName></iconName>
      <odePagStructureOrder>1</odePagStructureOrder>
      <odePagStructureProperties>
        <odePagStructureProperty>
          <key>visibility</key>
          <value>true</value>
        </odePagStructureProperty>
        <odePagStructureProperty>
          <key>teacherOnly</key>
          <value>false</value>
        </odePagStructureProperty>
        <odePagStructureProperty>
          <key>allowToggle</key>
          <value>true</value>
        </odePagStructureProperty>
        <odePagStructureProperty>
          <key>minimized</key>
          <value>false</value>
        </odePagStructureProperty>
        <odePagStructureProperty>
          <key>cssClass</key>
          <value></value>
        </odePagStructureProperty>
      </odePagStructureProperties>
      <odeComponents>
        <odeComponent>
          <odePageId>page-mo7fj2nq-af9ogzgnu</odePageId>
          <odeBlockId>block-1776529688982-gzbfasqjv</odeBlockId>
          <odeIdeviceId>idevice-1776529688980-luxzbpk0v</odeIdeviceId>
          <odeIdeviceTypeName>text</odeIdeviceTypeName>
          <htmlView><![CDATA[<div class="exe-text-template">
    <p><strong>Haz clic para visitar el Symbaloo de este proyecto.</strong></p>
<p><a href="https://www.symbaloo.com/shared/AAAABgfEhtAAA42ADpMvJg==" title="">https://www.symbaloo.com/shared/AAAABgfEhtAAA42ADpMvJg==</a></p>
</div>]]></htmlView>
          <jsonProperties><![CDATA[{"ideviceId":"idevice-1776529688980-luxzbpk0v","textInfoDurationInput":"","textInfoDurationTextInput":"Duración","textInfoParticipantsInput":"","textInfoParticipantsTextInput":"Agrupamiento","textTextarea":"<p><strong>Haz clic para visitar el Symbaloo de este proyecto.</strong></p>\n<p><a href=\"https://www.symbaloo.com/shared/AAAABgfEhtAAA42ADpMvJg==\" title=\"\">https://www.symbaloo.com/shared/AAAABgfEhtAAA42ADpMvJg==</a></p>","textFeedbackInput":"Mostrar retroalimentación","textFeedbackTextarea":""}]]></jsonProperties>
          <odeComponentsOrder>0</odeComponentsOrder>
          <odeComponentsProperties>
            <odeComponentsProperty>
              <key>visibility</key>
              <value>true</value>
            </odeComponentsProperty>
            <odeComponentsProperty>
              <key>teacherOnly</key>
              <value>false</value>
            </odeComponentsProperty>
            <odeComponentsProperty>
              <key>cssClass</key>
              <value></value>
            </odeComponentsProperty>
          </odeComponentsProperties>
        </odeComponent>
      </odeComponents>
    </odePagStructure>
  </odePagStructures>
</odeNavStructure>
<odeNavStructure>
  <odePageId>page-mo7fj2nq-1xw6oiezv</odePageId>
  <odeParentPageId>page-mo7fj2np-ozf28tvpv</odeParentPageId>
  <pageName>Pinterest</pageName>
  <odeNavStructureOrder>1</odeNavStructureOrder>
  <odeNavStructureProperties>
    <odeNavStructureProperty>
      <key>titlePage</key>
      <value>Pinterest</value>
    </odeNavStructureProperty>
    <odeNavStructureProperty>
      <key>visibility</key>
      <value>true</value>
    </odeNavStructureProperty>
    <odeNavStructureProperty>
      <key>highlight</key>
      <value>false</value>
    </odeNavStructureProperty>
    <odeNavStructureProperty>
      <key>hidePageTitle</key>
      <value>false</value>
    </odeNavStructureProperty>
    <odeNavStructureProperty>
      <key>editableInPage</key>
      <value>false</value>
    </odeNavStructureProperty>
    <odeNavStructureProperty>
      <key>titlePage</key>
      <value>Pinterest</value>
    </odeNavStructureProperty>
    <odeNavStructureProperty>
      <key>titleNode</key>
      <value></value>
    </odeNavStructureProperty>
  </odeNavStructureProperties>
  <odePagStructures>
    <odePagStructure>
      <odePageId>page-mo7fj2nq-1xw6oiezv</odePageId>
      <odeBlockId>block-1776529614243-ur5jppo7m</odeBlockId>
      <blockName>Web</blockName>
      <iconName></iconName>
      <odePagStructureOrder>1</odePagStructureOrder>
      <odePagStructureProperties>
        <odePagStructureProperty>
          <key>visibility</key>
          <value>true</value>
        </odePagStructureProperty>
        <odePagStructureProperty>
          <key>teacherOnly</key>
          <value>false</value>
        </odePagStructureProperty>
        <odePagStructureProperty>
          <key>allowToggle</key>
          <value>true</value>
        </odePagStructureProperty>
        <odePagStructureProperty>
          <key>minimized</key>
          <value>false</value>
        </odePagStructureProperty>
        <odePagStructureProperty>
          <key>cssClass</key>
          <value></value>
        </odePagStructureProperty>
      </odePagStructureProperties>
      <odeComponents>
        <odeComponent>
          <odePageId>page-mo7fj2nq-1xw6oiezv</odePageId>
          <odeBlockId>block-1776529614243-ur5jppo7m</odeBlockId>
          <odeIdeviceId>idevice-1776529614242-t66339s4a</odeIdeviceId>
          <odeIdeviceTypeName>text</odeIdeviceTypeName>
          <htmlView><![CDATA[<div class="exe-text-template">
    <p><strong><span dir="auto" style="vertical-align: inherit;"><span dir="auto" style="vertical-align: inherit;">Haz clic para visitar el Pinterest de este proyecto.</span></span></strong></p>
<p><a href="https://pin.it/318mDfeRJ" title="">https://pin.it/318mDfeRJ</a></p>
</div>]]></htmlView>
          <jsonProperties><![CDATA[{"ideviceId":"idevice-1776529614242-t66339s4a","textInfoDurationInput":"","textInfoDurationTextInput":"Duración","textInfoParticipantsInput":"","textInfoParticipantsTextInput":"Agrupamiento","textTextarea":"<p><strong><span dir=\"auto\" style=\"vertical-align: inherit;\"><span dir=\"auto\" style=\"vertical-align: inherit;\">Haz clic para visitar el Pinterest de este proyecto.</span></span></strong></p>\n<p><a href=\"https://pin.it/318mDfeRJ\" title=\"\">https://pin.it/318mDfeRJ</a></p>","textFeedbackInput":"Mostrar retroalimentación","textFeedbackTextarea":""}]]></jsonProperties>
          <odeComponentsOrder>0</odeComponentsOrder>
          <odeComponentsProperties>
            <odeComponentsProperty>
              <key>visibility</key>
              <value>true</value>
            </odeComponentsProperty>
            <odeComponentsProperty>
              <key>teacherOnly</key>
              <value>false</value>
            </odeComponentsProperty>
            <odeComponentsProperty>
              <key>cssClass</key>
              <value></value>
            </odeComponentsProperty>
          </odeComponentsProperties>
        </odeComponent>
      </odeComponents>
    </odePagStructure>
  </odePagStructures>
</odeNavStructure>
<odeNavStructure>
  <odePageId>page-mo7fj2nq-63mgymng0</odePageId>
  <odeParentPageId></odeParentPageId>
  <pageName>Línea temporal</pageName>
  <odeNavStructureOrder>4</odeNavStructureOrder>
  <odeNavStructureProperties>
    <odeNavStructureProperty>
      <key>titlePage</key>
      <value>Línea temporal</value>
    </odeNavStructureProperty>
    <odeNavStructureProperty>
      <key>visibility</key>
      <value>true</value>
    </odeNavStructureProperty>
    <odeNavStructureProperty>
      <key>highlight</key>
      <value>false</value>
    </odeNavStructureProperty>
    <odeNavStructureProperty>
      <key>hidePageTitle</key>
      <value>false</value>
    </odeNavStructureProperty>
    <odeNavStructureProperty>
      <key>editableInPage</key>
      <value>false</value>
    </odeNavStructureProperty>
    <odeNavStructureProperty>
      <key>titlePage</key>
      <value>Línea temporal</value>
    </odeNavStructureProperty>
    <odeNavStructureProperty>
      <key>titleNode</key>
      <value></value>
    </odeNavStructureProperty>
  </odeNavStructureProperties>
  <odePagStructures>
    <odePagStructure>
      <odePageId>page-mo7fj2nq-63mgymng0</odePageId>
      <odeBlockId>block-1776529850292-4ssuz7g9j</odeBlockId>
      <blockName>Línea temporal</blockName>
      <iconName></iconName>
      <odePagStructureOrder>1</odePagStructureOrder>
      <odePagStructureProperties>
        <odePagStructureProperty>
          <key>visibility</key>
          <value>true</value>
        </odePagStructureProperty>
        <odePagStructureProperty>
          <key>teacherOnly</key>
          <value>false</value>
        </odePagStructureProperty>
        <odePagStructureProperty>
          <key>allowToggle</key>
          <value>true</value>
        </odePagStructureProperty>
        <odePagStructureProperty>
          <key>minimized</key>
          <value>false</value>
        </odePagStructureProperty>
        <odePagStructureProperty>
          <key>cssClass</key>
          <value></value>
        </odePagStructureProperty>
      </odePagStructureProperties>
      <odeComponents>
        <odeComponent>
          <odePageId>page-mo7fj2nq-63mgymng0</odePageId>
          <odeBlockId>block-1776529850292-4ssuz7g9j</odeBlockId>
          <odeIdeviceId>idevice-1776529850291-8g0ed669s</odeIdeviceId>
          <odeIdeviceTypeName>image-gallery</odeIdeviceTypeName>
          <htmlView><![CDATA[<!-- Idevice Example template start -->
<div class="exe-image-gallery-template">
  <!-- Idevice content start -->
  
            <div class="imageGallery-IDevice">
                <div class="imageGallery-body"><div id="imageContainer_0" class="imageContainer"> <a idevice-id="idevice-1776529850291-8g0ed669s" title="" href="{{context_path}}/content/resources/Tarea 7.1 Línea temporal (1).png" class="imageLink">  <div class="imageElement">   <img src="{{context_path}}/content/resources/Tarea 7.1 Línea temporal (1).png" height="128" width="128" title="" alt="" titlelink="" author="" authorlink="" license="" licenselink=""/>  </div> </a></div>
                </div>
            </div>
  <!-- Idevice content end -->
</div>
<!-- Idevice Example template end -->]]></htmlView>
          <jsonProperties><![CDATA[{"ideviceId":"idevice-1776529850291-8g0ed669s","img_0":{"img":"{{context_path}}/content/resources/Tarea 7.1 Línea temporal (1).png","thumbnail":"{{context_path}}/content/resources/Tarea 7.1 Línea temporal (1).png","title":"","linktitle":"","author":"","linkauthor":"","license":""}}]]></jsonProperties>
          <odeComponentsOrder>0</odeComponentsOrder>
          <odeComponentsProperties>
            <odeComponentsProperty>
              <key>visibility</key>
              <value>true</value>
            </odeComponentsProperty>
            <odeComponentsProperty>
              <key>teacherOnly</key>
              <value>false</value>
            </odeComponentsProperty>
            <odeComponentsProperty>
              <key>cssClass</key>
              <value></value>
            </odeComponentsProperty>
          </odeComponentsProperties>
        </odeComponent>
      </odeComponents>
    </odePagStructure>
  </odePagStructures>
</odeNavStructure>
<odeNavStructure>
  <odePageId>page-mo7fj2nr-2wrdwe4gk</odePageId>
  <odeParentPageId></odeParentPageId>
  <pageName>Criterios de evaluación</pageName>
  <odeNavStructureOrder>5</odeNavStructureOrder>
  <odeNavStructureProperties>
    <odeNavStructureProperty>
      <key>titlePage</key>
      <value>Criterios de evaluación</value>
    </odeNavStructureProperty>
    <odeNavStructureProperty>
      <key>visibility</key>
      <value>true</value>
    </odeNavStructureProperty>
    <odeNavStructureProperty>
      <key>highlight</key>
      <value>false</value>
    </odeNavStructureProperty>
    <odeNavStructureProperty>
      <key>hidePageTitle</key>
      <value>false</value>
    </odeNavStructureProperty>
    <odeNavStructureProperty>
      <key>editableInPage</key>
      <value>false</value>
    </odeNavStructureProperty>
    <odeNavStructureProperty>
      <key>titlePage</key>
      <value>Criterios de evaluación</value>
    </odeNavStructureProperty>
    <odeNavStructureProperty>
      <key>titleNode</key>
      <value></value>
    </odeNavStructureProperty>
  </odeNavStructureProperties>
  <odePagStructures>
    <odePagStructure>
      <odePageId>page-mo7fj2nr-2wrdwe4gk</odePageId>
      <odeBlockId>block-1776530439961-ph8ro6eqc</odeBlockId>
      <blockName>Criterios y actividades</blockName>
      <iconName></iconName>
      <odePagStructureOrder>1</odePagStructureOrder>
      <odePagStructureProperties>
        <odePagStructureProperty>
          <key>visibility</key>
          <value>true</value>
        </odePagStructureProperty>
        <odePagStructureProperty>
          <key>teacherOnly</key>
          <value>false</value>
        </odePagStructureProperty>
        <odePagStructureProperty>
          <key>allowToggle</key>
          <value>true</value>
        </odePagStructureProperty>
        <odePagStructureProperty>
          <key>minimized</key>
          <value>false</value>
        </odePagStructureProperty>
        <odePagStructureProperty>
          <key>cssClass</key>
          <value></value>
        </odePagStructureProperty>
      </odePagStructureProperties>
      <odeComponents>
        <odeComponent>
          <odePageId>page-mo7fj2nr-2wrdwe4gk</odePageId>
          <odeBlockId>block-1776530439961-ph8ro6eqc</odeBlockId>
          <odeIdeviceId>idevice-1776530439959-apoum1w7t</odeIdeviceId>
          <odeIdeviceTypeName>image-gallery</odeIdeviceTypeName>
          <htmlView><![CDATA[<!-- Idevice Example template start -->
<div class="exe-image-gallery-template">
  <!-- Idevice content start -->
  
            <div class="imageGallery-IDevice">
                <div class="imageGallery-body"><div id="imageContainer_0" class="imageContainer"> <a idevice-id="idevice-1776530439959-apoum1w7t" title="" href="{{context_path}}/content/resources/Captura de pantalla 2026-04-18 184032.png" class="imageLink">  <div class="imageElement">   <img src="{{context_path}}/content/resources/Captura de pantalla 2026-04-18 184032.png" height="128" width="128" title="" alt="" titlelink="" author="" authorlink="" license="" licenselink=""/>  </div> </a></div>
                </div>
            </div>
  <!-- Idevice content end -->
</div>
<!-- Idevice Example template end -->]]></htmlView>
          <jsonProperties><![CDATA[{"ideviceId":"idevice-1776530439959-apoum1w7t","img_0":{"img":"{{context_path}}/content/resources/Captura de pantalla 2026-04-18 184032.png","thumbnail":"{{context_path}}/content/resources/Captura de pantalla 2026-04-18 184032.png","title":"","linktitle":"","author":"","linkauthor":"","license":""}}]]></jsonProperties>
          <odeComponentsOrder>0</odeComponentsOrder>
          <odeComponentsProperties>
            <odeComponentsProperty>
              <key>visibility</key>
              <value>true</value>
            </odeComponentsProperty>
            <odeComponentsProperty>
              <key>teacherOnly</key>
              <value>false</value>
            </odeComponentsProperty>
            <odeComponentsProperty>
              <key>cssClass</key>
              <value></value>
            </odeComponentsProperty>
          </odeComponentsProperties>
        </odeComponent>
      </odeComponents>
    </odePagStructure>
  </odePagStructures>
</odeNavStructure>
<odeNavStructure>
  <odePageId>page-mo7fj2nr-onlivmpcp</odePageId>
  <odeParentPageId></odeParentPageId>
  <pageName>Instrumentos de evaluación</pageName>
  <odeNavStructureOrder>6</odeNavStructureOrder>
  <odeNavStructureProperties>
    <odeNavStructureProperty>
      <key>titlePage</key>
      <value>Instrumentos de evaluación</value>
    </odeNavStructureProperty>
    <odeNavStructureProperty>
      <key>visibility</key>
      <value>true</value>
    </odeNavStructureProperty>
    <odeNavStructureProperty>
      <key>highlight</key>
      <value>false</value>
    </odeNavStructureProperty>
    <odeNavStructureProperty>
      <key>hidePageTitle</key>
      <value>false</value>
    </odeNavStructureProperty>
    <odeNavStructureProperty>
      <key>editableInPage</key>
      <value>false</value>
    </odeNavStructureProperty>
    <odeNavStructureProperty>
      <key>titlePage</key>
      <value>Instrumentos de evaluación</value>
    </odeNavStructureProperty>
    <odeNavStructureProperty>
      <key>titleNode</key>
      <value></value>
    </odeNavStructureProperty>
  </odeNavStructureProperties>
  <odePagStructures>
  </odePagStructures>
</odeNavStructure>
<odeNavStructure>
  <odePageId>page-mo7fj2ns-x8d1f0ki0</odePageId>
  <odeParentPageId>page-mo7fj2nr-onlivmpcp</odeParentPageId>
  <pageName>Rúbrica 1</pageName>
  <odeNavStructureOrder>0</odeNavStructureOrder>
  <odeNavStructureProperties>
    <odeNavStructureProperty>
      <key>titlePage</key>
      <value>Rúbrica 1</value>
    </odeNavStructureProperty>
    <odeNavStructureProperty>
      <key>visibility</key>
      <value>true</value>
    </odeNavStructureProperty>
    <odeNavStructureProperty>
      <key>highlight</key>
      <value>false</value>
    </odeNavStructureProperty>
    <odeNavStructureProperty>
      <key>hidePageTitle</key>
      <value>false</value>
    </odeNavStructureProperty>
    <odeNavStructureProperty>
      <key>editableInPage</key>
      <value>false</value>
    </odeNavStructureProperty>
    <odeNavStructureProperty>
      <key>titlePage</key>
      <value>Rúbrica 1</value>
    </odeNavStructureProperty>
    <odeNavStructureProperty>
      <key>titleNode</key>
      <value></value>
    </odeNavStructureProperty>
  </odeNavStructureProperties>
  <odePagStructures>
    <odePagStructure>
      <odePageId>page-mo7fj2ns-x8d1f0ki0</odePageId>
      <odeBlockId>block-1776530802165-szhpap29o</odeBlockId>
      <blockName>Galería de imágenes</blockName>
      <iconName></iconName>
      <odePagStructureOrder>1</odePagStructureOrder>
      <odePagStructureProperties>
        <odePagStructureProperty>
          <key>visibility</key>
          <value>true</value>
        </odePagStructureProperty>
        <odePagStructureProperty>
          <key>teacherOnly</key>
          <value>false</value>
        </odePagStructureProperty>
        <odePagStructureProperty>
          <key>allowToggle</key>
          <value>true</value>
        </odePagStructureProperty>
        <odePagStructureProperty>
          <key>minimized</key>
          <value>false</value>
        </odePagStructureProperty>
        <odePagStructureProperty>
          <key>cssClass</key>
          <value></value>
        </odePagStructureProperty>
      </odePagStructureProperties>
      <odeComponents>
        <odeComponent>
          <odePageId>page-mo7fj2ns-x8d1f0ki0</odePageId>
          <odeBlockId>block-1776530802165-szhpap29o</odeBlockId>
          <odeIdeviceId>idevice-1776530802163-qactvl4vv</odeIdeviceId>
          <odeIdeviceTypeName>image-gallery</odeIdeviceTypeName>
          <htmlView><![CDATA[<!-- Idevice Example template start -->
<div class="exe-image-gallery-template">
  <!-- Idevice content start -->
  
            <div class="imageGallery-IDevice">
                <div class="imageGallery-body"><div id="imageContainer_0" class="imageContainer"> <a idevice-id="idevice-1776530802163-qactvl4vv" title="" href="{{context_path}}/content/resources/2.png" class="imageLink">  <div class="imageElement">   <img src="{{context_path}}/content/resources/2.png" height="128" width="128" title="" alt="" titlelink="" author="" authorlink="" license="" licenselink=""/>  </div> </a></div>
                </div>
            </div>
  <!-- Idevice content end -->
</div>
<!-- Idevice Example template end -->]]></htmlView>
          <jsonProperties><![CDATA[{"ideviceId":"idevice-1776530802163-qactvl4vv","img_0":{"img":"{{context_path}}/content/resources/2.png","thumbnail":"{{context_path}}/content/resources/2.png","title":"","linktitle":"","author":"","linkauthor":"","license":""}}]]></jsonProperties>
          <odeComponentsOrder>0</odeComponentsOrder>
          <odeComponentsProperties>
            <odeComponentsProperty>
              <key>visibility</key>
              <value>true</value>
            </odeComponentsProperty>
            <odeComponentsProperty>
              <key>teacherOnly</key>
              <value>false</value>
            </odeComponentsProperty>
            <odeComponentsProperty>
              <key>cssClass</key>
              <value></value>
            </odeComponentsProperty>
          </odeComponentsProperties>
        </odeComponent>
      </odeComponents>
    </odePagStructure>
  </odePagStructures>
</odeNavStructure>
<odeNavStructure>
  <odePageId>page-mo7fj2ns-gabldwsjj</odePageId>
  <odeParentPageId>page-mo7fj2nr-onlivmpcp</odeParentPageId>
  <pageName>Rúbrica 2</pageName>
  <odeNavStructureOrder>1</odeNavStructureOrder>
  <odeNavStructureProperties>
    <odeNavStructureProperty>
      <key>titlePage</key>
      <value>Rúbrica 2</value>
    </odeNavStructureProperty>
    <odeNavStructureProperty>
      <key>visibility</key>
      <value>true</value>
    </odeNavStructureProperty>
    <odeNavStructureProperty>
      <key>highlight</key>
      <value>false</value>
    </odeNavStructureProperty>
    <odeNavStructureProperty>
      <key>hidePageTitle</key>
      <value>false</value>
    </odeNavStructureProperty>
    <odeNavStructureProperty>
      <key>editableInPage</key>
      <value>false</value>
    </odeNavStructureProperty>
    <odeNavStructureProperty>
      <key>titlePage</key>
      <value>Rúbrica 2</value>
    </odeNavStructureProperty>
    <odeNavStructureProperty>
      <key>titleNode</key>
      <value></value>
    </odeNavStructureProperty>
  </odeNavStructureProperties>
  <odePagStructures>
    <odePagStructure>
      <odePageId>page-mo7fj2ns-gabldwsjj</odePageId>
      <odeBlockId>block-1776530878060-vobgb4waj</odeBlockId>
      <blockName>Galería de imágenes</blockName>
      <iconName></iconName>
      <odePagStructureOrder>1</odePagStructureOrder>
      <odePagStructureProperties>
        <odePagStructureProperty>
          <key>visibility</key>
          <value>true</value>
        </odePagStructureProperty>
        <odePagStructureProperty>
          <key>teacherOnly</key>
          <value>false</value>
        </odePagStructureProperty>
        <odePagStructureProperty>
          <key>allowToggle</key>
          <value>true</value>
        </odePagStructureProperty>
        <odePagStructureProperty>
          <key>minimized</key>
          <value>false</value>
        </odePagStructureProperty>
        <odePagStructureProperty>
          <key>cssClass</key>
          <value></value>
        </odePagStructureProperty>
      </odePagStructureProperties>
      <odeComponents>
        <odeComponent>
          <odePageId>page-mo7fj2ns-gabldwsjj</odePageId>
          <odeBlockId>block-1776530878060-vobgb4waj</odeBlockId>
          <odeIdeviceId>idevice-1776530878059-gtfx36p8j</odeIdeviceId>
          <odeIdeviceTypeName>image-gallery</odeIdeviceTypeName>
          <htmlView><![CDATA[<!-- Idevice Example template start -->
<div class="exe-image-gallery-template">
  <!-- Idevice content start -->
  
            <div class="imageGallery-IDevice">
                <div class="imageGallery-body"><div id="imageContainer_0" class="imageContainer"> <a idevice-id="idevice-1776530878059-gtfx36p8j" title="" href="{{context_path}}/content/resources/3.png" class="imageLink">  <div class="imageElement">   <img src="{{context_path}}/content/resources/3.png" height="128" width="128" title="" alt="" titlelink="" author="" authorlink="" license="" licenselink=""/>  </div> </a></div>
                </div>
            </div>
  <!-- Idevice content end -->
</div>
<!-- Idevice Example template end -->]]></htmlView>
          <jsonProperties><![CDATA[{"ideviceId":"idevice-1776530878059-gtfx36p8j","img_0":{"img":"{{context_path}}/content/resources/3.png","thumbnail":"{{context_path}}/content/resources/3.png","title":"","linktitle":"","author":"","linkauthor":"","license":""}}]]></jsonProperties>
          <odeComponentsOrder>0</odeComponentsOrder>
          <odeComponentsProperties>
            <odeComponentsProperty>
              <key>visibility</key>
              <value>true</value>
            </odeComponentsProperty>
            <odeComponentsProperty>
              <key>teacherOnly</key>
              <value>false</value>
            </odeComponentsProperty>
            <odeComponentsProperty>
              <key>cssClass</key>
              <value></value>
            </odeComponentsProperty>
          </odeComponentsProperties>
        </odeComponent>
      </odeComponents>
    </odePagStructure>
  </odePagStructures>
</odeNavStructure>
<odeNavStructure>
  <odePageId>page-mo7fj2nt-d35eraoss</odePageId>
  <odeParentPageId>page-mo7fj2nr-onlivmpcp</odeParentPageId>
  <pageName>Escala de Observación 1</pageName>
  <odeNavStructureOrder>2</odeNavStructureOrder>
  <odeNavStructureProperties>
    <odeNavStructureProperty>
      <key>titlePage</key>
      <value>Escala de Observación 1</value>
    </odeNavStructureProperty>
    <odeNavStructureProperty>
      <key>visibility</key>
      <value>true</value>
    </odeNavStructureProperty>
    <odeNavStructureProperty>
      <key>highlight</key>
      <value>false</value>
    </odeNavStructureProperty>
    <odeNavStructureProperty>
      <key>hidePageTitle</key>
      <value>false</value>
    </odeNavStructureProperty>
    <odeNavStructureProperty>
      <key>editableInPage</key>
      <value>false</value>
    </odeNavStructureProperty>
    <odeNavStructureProperty>
      <key>titlePage</key>
      <value>Escala de Observación 1</value>
    </odeNavStructureProperty>
    <odeNavStructureProperty>
      <key>titleNode</key>
      <value></value>
    </odeNavStructureProperty>
  </odeNavStructureProperties>
  <odePagStructures>
    <odePagStructure>
      <odePageId>page-mo7fj2nt-d35eraoss</odePageId>
      <odeBlockId>block-1776530897165-235bm27o1</odeBlockId>
      <blockName>Galería de imágenes</blockName>
      <iconName></iconName>
      <odePagStructureOrder>1</odePagStructureOrder>
      <odePagStructureProperties>
        <odePagStructureProperty>
          <key>visibility</key>
          <value>true</value>
        </odePagStructureProperty>
        <odePagStructureProperty>
          <key>teacherOnly</key>
          <value>false</value>
        </odePagStructureProperty>
        <odePagStructureProperty>
          <key>allowToggle</key>
          <value>true</value>
        </odePagStructureProperty>
        <odePagStructureProperty>
          <key>minimized</key>
          <value>false</value>
        </odePagStructureProperty>
        <odePagStructureProperty>
          <key>cssClass</key>
          <value></value>
        </odePagStructureProperty>
      </odePagStructureProperties>
      <odeComponents>
        <odeComponent>
          <odePageId>page-mo7fj2nt-d35eraoss</odePageId>
          <odeBlockId>block-1776530897165-235bm27o1</odeBlockId>
          <odeIdeviceId>idevice-1776530897164-q93hrawo3</odeIdeviceId>
          <odeIdeviceTypeName>image-gallery</odeIdeviceTypeName>
          <htmlView><![CDATA[<!-- Idevice Example template start -->
<div class="exe-image-gallery-template">
  <!-- Idevice content start -->
  
            <div class="imageGallery-IDevice">
                <div class="imageGallery-body"><div id="imageContainer_0" class="imageContainer"> <a idevice-id="idevice-1776530897164-q93hrawo3" title="" href="{{context_path}}/content/resources/5.png" class="imageLink">  <div class="imageElement">   <img src="{{context_path}}/content/resources/5.png" height="128" width="128" title="" alt="" titlelink="" author="" authorlink="" license="" licenselink=""/>  </div> </a></div>
                </div>
            </div>
  <!-- Idevice content end -->
</div>
<!-- Idevice Example template end -->]]></htmlView>
          <jsonProperties><![CDATA[{"ideviceId":"idevice-1776530897164-q93hrawo3","img_0":{"img":"{{context_path}}/content/resources/5.png","thumbnail":"{{context_path}}/content/resources/5.png","title":"","linktitle":"","author":"","linkauthor":"","license":""}}]]></jsonProperties>
          <odeComponentsOrder>0</odeComponentsOrder>
          <odeComponentsProperties>
            <odeComponentsProperty>
              <key>visibility</key>
              <value>true</value>
            </odeComponentsProperty>
            <odeComponentsProperty>
              <key>teacherOnly</key>
              <value>false</value>
            </odeComponentsProperty>
            <odeComponentsProperty>
              <key>cssClass</key>
              <value></value>
            </odeComponentsProperty>
          </odeComponentsProperties>
        </odeComponent>
      </odeComponents>
    </odePagStructure>
  </odePagStructures>
</odeNavStructure>
<odeNavStructure>
  <odePageId>page-mo7fj2nt-mct4svb6h</odePageId>
  <odeParentPageId>page-mo7fj2nr-onlivmpcp</odeParentPageId>
  <pageName>Escala de observación 2</pageName>
  <odeNavStructureOrder>3</odeNavStructureOrder>
  <odeNavStructureProperties>
    <odeNavStructureProperty>
      <key>titlePage</key>
      <value>Escala de observación 2</value>
    </odeNavStructureProperty>
    <odeNavStructureProperty>
      <key>visibility</key>
      <value>true</value>
    </odeNavStructureProperty>
    <odeNavStructureProperty>
      <key>highlight</key>
      <value>false</value>
    </odeNavStructureProperty>
    <odeNavStructureProperty>
      <key>hidePageTitle</key>
      <value>false</value>
    </odeNavStructureProperty>
    <odeNavStructureProperty>
      <key>editableInPage</key>
      <value>false</value>
    </odeNavStructureProperty>
    <odeNavStructureProperty>
      <key>titlePage</key>
      <value>Escala de observación 2</value>
    </odeNavStructureProperty>
    <odeNavStructureProperty>
      <key>titleNode</key>
      <value>Escala de observación 2</value>
    </odeNavStructureProperty>
  </odeNavStructureProperties>
  <odePagStructures>
    <odePagStructure>
      <odePageId>page-mo7fj2nt-mct4svb6h</odePageId>
      <odeBlockId>block-1776530914873-d0v0kmn3w</odeBlockId>
      <blockName>Galería de imágenes</blockName>
      <iconName></iconName>
      <odePagStructureOrder>1</odePagStructureOrder>
      <odePagStructureProperties>
        <odePagStructureProperty>
          <key>visibility</key>
          <value>true</value>
        </odePagStructureProperty>
        <odePagStructureProperty>
          <key>teacherOnly</key>
          <value>false</value>
        </odePagStructureProperty>
        <odePagStructureProperty>
          <key>allowToggle</key>
          <value>true</value>
        </odePagStructureProperty>
        <odePagStructureProperty>
          <key>minimized</key>
          <value>false</value>
        </odePagStructureProperty>
        <odePagStructureProperty>
          <key>cssClass</key>
          <value></value>
        </odePagStructureProperty>
      </odePagStructureProperties>
      <odeComponents>
        <odeComponent>
          <odePageId>page-mo7fj2nt-mct4svb6h</odePageId>
          <odeBlockId>block-1776530914873-d0v0kmn3w</odeBlockId>
          <odeIdeviceId>idevice-1776530914873-ywbkk0pm6</odeIdeviceId>
          <odeIdeviceTypeName>image-gallery</odeIdeviceTypeName>
          <htmlView><![CDATA[<!-- Idevice Example template start -->
<div class="exe-image-gallery-template">
  <!-- Idevice content start -->
  
            <div class="imageGallery-IDevice">
                <div class="imageGallery-body"><div id="imageContainer_0" class="imageContainer"> <a idevice-id="idevice-1776530914873-ywbkk0pm6" title="" href="{{context_path}}/content/resources/6.png" class="imageLink">  <div class="imageElement">   <img src="{{context_path}}/content/resources/6.png" height="128" width="128" title="" alt="" titlelink="" author="" authorlink="" license="" licenselink=""/>  </div> </a></div>
                </div>
            </div>
  <!-- Idevice content end -->
</div>
<!-- Idevice Example template end -->]]></htmlView>
          <jsonProperties><![CDATA[{"ideviceId":"idevice-1776530914873-ywbkk0pm6","img_0":{"img":"{{context_path}}/content/resources/6.png","thumbnail":"{{context_path}}/content/resources/6.png","title":"","linktitle":"","author":"","linkauthor":"","license":""}}]]></jsonProperties>
          <odeComponentsOrder>0</odeComponentsOrder>
          <odeComponentsProperties>
            <odeComponentsProperty>
              <key>visibility</key>
              <value>true</value>
            </odeComponentsProperty>
            <odeComponentsProperty>
              <key>teacherOnly</key>
              <value>false</value>
            </odeComponentsProperty>
            <odeComponentsProperty>
              <key>cssClass</key>
              <value></value>
            </odeComponentsProperty>
          </odeComponentsProperties>
        </odeComponent>
      </odeComponents>
    </odePagStructure>
  </odePagStructures>
</odeNavStructure>
<odeNavStructure>
  <odePageId>page-mo7fj2nt-iaiix3sud</odePageId>
  <odeParentPageId>page-mo7fj2nr-onlivmpcp</odeParentPageId>
  <pageName>Autoevaluación con caritas</pageName>
  <odeNavStructureOrder>4</odeNavStructureOrder>
  <odeNavStructureProperties>
    <odeNavStructureProperty>
      <key>titlePage</key>
      <value>Autoevaluación con caritas</value>
    </odeNavStructureProperty>
    <odeNavStructureProperty>
      <key>visibility</key>
      <value>true</value>
    </odeNavStructureProperty>
    <odeNavStructureProperty>
      <key>highlight</key>
      <value>false</value>
    </odeNavStructureProperty>
    <odeNavStructureProperty>
      <key>hidePageTitle</key>
      <value>false</value>
    </odeNavStructureProperty>
    <odeNavStructureProperty>
      <key>editableInPage</key>
      <value>false</value>
    </odeNavStructureProperty>
    <odeNavStructureProperty>
      <key>titlePage</key>
      <value>Autoevaluación con caritas</value>
    </odeNavStructureProperty>
    <odeNavStructureProperty>
      <key>titleNode</key>
      <value>Autoevaluación con caritas</value>
    </odeNavStructureProperty>
  </odeNavStructureProperties>
  <odePagStructures>
    <odePagStructure>
      <odePageId>page-mo7fj2nt-iaiix3sud</odePageId>
      <odeBlockId>block-1776530940437-vz6pjvn25</odeBlockId>
      <blockName>Galería de imágenes</blockName>
      <iconName></iconName>
      <odePagStructureOrder>1</odePagStructureOrder>
      <odePagStructureProperties>
        <odePagStructureProperty>
          <key>visibility</key>
          <value>true</value>
        </odePagStructureProperty>
        <odePagStructureProperty>
          <key>teacherOnly</key>
          <value>false</value>
        </odePagStructureProperty>
        <odePagStructureProperty>
          <key>allowToggle</key>
          <value>true</value>
        </odePagStructureProperty>
        <odePagStructureProperty>
          <key>minimized</key>
          <value>false</value>
        </odePagStructureProperty>
        <odePagStructureProperty>
          <key>cssClass</key>
          <value></value>
        </odePagStructureProperty>
      </odePagStructureProperties>
      <odeComponents>
        <odeComponent>
          <odePageId>page-mo7fj2nt-iaiix3sud</odePageId>
          <odeBlockId>block-1776530940437-vz6pjvn25</odeBlockId>
          <odeIdeviceId>idevice-1776530940436-7yxsd8h5t</odeIdeviceId>
          <odeIdeviceTypeName>image-gallery</odeIdeviceTypeName>
          <htmlView><![CDATA[<!-- Idevice Example template start -->
<div class="exe-image-gallery-template">
  <!-- Idevice content start -->
  
            <div class="imageGallery-IDevice">
                <div class="imageGallery-body"><div id="imageContainer_0" class="imageContainer"> <a idevice-id="idevice-1776530940436-7yxsd8h5t" title="" href="{{context_path}}/content/resources/8.png" class="imageLink">  <div class="imageElement">   <img src="{{context_path}}/content/resources/8.png" height="128" width="128" title="" alt="" titlelink="" author="" authorlink="" license="" licenselink=""/>  </div> </a></div>
                </div>
            </div>
  <!-- Idevice content end -->
</div>
<!-- Idevice Example template end -->]]></htmlView>
          <jsonProperties><![CDATA[{"ideviceId":"idevice-1776530940436-7yxsd8h5t","img_0":{"img":"{{context_path}}/content/resources/8.png","thumbnail":"{{context_path}}/content/resources/8.png","title":"","linktitle":"","author":"","linkauthor":"","license":""}}]]></jsonProperties>
          <odeComponentsOrder>0</odeComponentsOrder>
          <odeComponentsProperties>
            <odeComponentsProperty>
              <key>visibility</key>
              <value>true</value>
            </odeComponentsProperty>
            <odeComponentsProperty>
              <key>teacherOnly</key>
              <value>false</value>
            </odeComponentsProperty>
            <odeComponentsProperty>
              <key>cssClass</key>
              <value></value>
            </odeComponentsProperty>
          </odeComponentsProperties>
        </odeComponent>
      </odeComponents>
    </odePagStructure>
  </odePagStructures>
</odeNavStructure>
<odeNavStructure>
  <odePageId>page-mo7fj2nt-q9ce2g3nh</odePageId>
  <odeParentPageId></odeParentPageId>
  <pageName>Créditos</pageName>
  <odeNavStructureOrder>7</odeNavStructureOrder>
  <odeNavStructureProperties>
    <odeNavStructureProperty>
      <key>titlePage</key>
      <value>Créditos</value>
    </odeNavStructureProperty>
    <odeNavStructureProperty>
      <key>visibility</key>
      <value>true</value>
    </odeNavStructureProperty>
    <odeNavStructureProperty>
      <key>highlight</key>
      <value>false</value>
    </odeNavStructureProperty>
    <odeNavStructureProperty>
      <key>hidePageTitle</key>
      <value>false</value>
    </odeNavStructureProperty>
    <odeNavStructureProperty>
      <key>editableInPage</key>
      <value>false</value>
    </odeNavStructureProperty>
    <odeNavStructureProperty>
      <key>titlePage</key>
      <value>Créditos</value>
    </odeNavStructureProperty>
    <odeNavStructureProperty>
      <key>titleNode</key>
      <value></value>
    </odeNavStructureProperty>
  </odeNavStructureProperties>
  <odePagStructures>
    <odePagStructure>
      <odePageId>page-mo7fj2nt-q9ce2g3nh</odePageId>
      <odeBlockId>block-1776531002366-35a35bgyx</odeBlockId>
      <blockName>Descargar el archivo fuente</blockName>
      <iconName></iconName>
      <odePagStructureOrder>1</odePagStructureOrder>
      <odePagStructureProperties>
        <odePagStructureProperty>
          <key>visibility</key>
          <value>true</value>
        </odePagStructureProperty>
        <odePagStructureProperty>
          <key>teacherOnly</key>
          <value>false</value>
        </odePagStructureProperty>
        <odePagStructureProperty>
          <key>allowToggle</key>
          <value>true</value>
        </odePagStructureProperty>
        <odePagStructureProperty>
          <key>minimized</key>
          <value>false</value>
        </odePagStructureProperty>
        <odePagStructureProperty>
          <key>cssClass</key>
          <value></value>
        </odePagStructureProperty>
      </odePagStructureProperties>
      <odeComponents>
        <odeComponent>
          <odePageId>page-mo7fj2nt-q9ce2g3nh</odePageId>
          <odeBlockId>block-1776531002366-35a35bgyx</odeBlockId>
          <odeIdeviceId>idevice-1776531002364-3x68six0l</odeIdeviceId>
          <odeIdeviceTypeName>download-source-file</odeIdeviceTypeName>
          <htmlView><![CDATA[<div class="exe-download-package-instructions"><table class="exe-table exe-package-info"><caption>Información general sobre este recurso educativo</caption>
<tbody>
<tr>
<th>Título</th>
<td class="mceNonEditable exe-prop-locked"><span class="exe-prop-title">Pequeños exploradores saludables</span></td>
</tr>
<tr>
<th>Descripción</th>
<td class="mceNonEditable exe-prop-locked"><span class="exe-prop-description">- Centro de Interés: El conocimiento del propio cuerpo y la adquisición de hábitos de alimentación saludable.
- Nivel: 3 años.
- Temporalización: 3 semanas (aproximadamente 9 sesiones de 30 minutos).
- Materias Implicadas: Áreas de Crecimiento en Armonía, Descubrimiento y Exploración del Entorno y Comunicación y Representación de la Realidad.
- Idioma: Castellano.
- Descripción General: El alumnado identificará las partes principales de su cuerpo y clasificará alimentos saludables y no saludables mediante juegos en la pizarra digital interactiva (PDI) y actividades sensoriales manipulativas.
- Justificación (Basada en la rutina de problemas técnicos): La elección de estos recursos digitales se debe a que se busca crear un entorno de aprendizaje activo y, al mismo tiempo, preparado ante posibles problemas técnicos. Por eso, se han escogido herramientas que cargan rápido y que pueden usarse sin conexión a internet, evitando así interrupciones. Además, las actividades tienen un diseño sencillo, ya que los niños de 3 años aún están desarrollando su habilidad para manejar objetos con precisión. Por este motivo, los elementos son grandes y fáciles de mover, de manera que puedan utilizarlos sin dificultad, incluso si la pantalla no está perfectamente calibrada.</span></td>
</tr>
<tr>
<th>Autoría</th>
<td class="mceNonEditable exe-prop-locked"><span class="exe-prop-author">Iria Flores</span></td>
</tr>
<tr>
<th>Licencia</th>
<td class="mceNonEditable exe-prop-locked"><span class="exe-prop-license">creative commons: attribution - share alike 4.0</span></td>
</tr>
</tbody>
</table>
<p style="text-align: center;">Este contenido fue creado con <a href="https://exelearning.net/">eXeLearning</a>, el editor libre y de fuente abierta diseñado para crear recursos educativos.</p></div><p class="exe-download-package-link"><a download="exe-package:elp-name" href="exe-package:elp" style="background-color:#107275;color:#ffffff;">Descargar el archivo .elpx</a></p>]]></htmlView>
          <jsonProperties></jsonProperties>
          <odeComponentsOrder>0</odeComponentsOrder>
          <odeComponentsProperties>
            <odeComponentsProperty>
              <key>visibility</key>
              <value>true</value>
            </odeComponentsProperty>
            <odeComponentsProperty>
              <key>teacherOnly</key>
              <value>false</value>
            </odeComponentsProperty>
            <odeComponentsProperty>
              <key>cssClass</key>
              <value></value>
            </odeComponentsProperty>
          </odeComponentsProperties>
        </odeComponent>
      </odeComponents>
    </odePagStructure>
  </odePagStructures>
</odeNavStructure>
</odeNavStructures>
</ode>